{
  "manifestVersion": "3.2",
  "proxies": [
    {
      "address": "0x418F45298CDB0B5243e90aBA3380449496Db1257",
      "txHash": "0x1f56ae886e1f6c702b1199a3b247ce67265b37d57870bb8d28331f6a693d6680",
      "kind": "uups"
    }
  ],
  "impls": {
    "354c529b5e9aa7764520a16ec68af2d6e10c7270c68227e28cf12194eee3d1c3": {
      "address": "0x01bE153b2a16f3724F746bB61817B3edefa5c013",
      "txHash": "0x95e71294737ffc7b7e3acaf3622a27509ca0c749151dc75d5d0bb8b212fb49ed",
      "layout": {
        "storage": [
          {
            "contract": "Initializable",
            "label": "_initialized",
            "type": "t_bool",
            "src": "@openzeppelin/contracts-upgradeable/proxy/utils/Initializable.sol:21"
          },
          {
            "contract": "Initializable",
            "label": "_initializing",
            "type": "t_bool",
            "src": "@openzeppelin/contracts-upgradeable/proxy/utils/Initializable.sol:26"
          },
          {
            "contract": "ContextUpgradeable",
            "label": "__gap",
            "type": "t_array(t_uint256)50_storage",
            "src": "@openzeppelin/contracts-upgradeable/utils/ContextUpgradeable.sol:30"
          },
          {
            "contract": "ERC20Upgradeable",
            "label": "_balances",
            "type": "t_mapping(t_address,t_uint256)",
            "src": "@openzeppelin/contracts-upgradeable/token/ERC20/ERC20Upgradeable.sol:36"
          },
          {
            "contract": "ERC20Upgradeable",
            "label": "_allowances",
            "type": "t_mapping(t_address,t_mapping(t_address,t_uint256))",
            "src": "@openzeppelin/contracts-upgradeable/token/ERC20/ERC20Upgradeable.sol:38"
          },
          {
            "contract": "ERC20Upgradeable",
            "label": "_totalSupply",
            "type": "t_uint256",
            "src": "@openzeppelin/contracts-upgradeable/token/ERC20/ERC20Upgradeable.sol:40"
          },
          {
            "contract": "ERC20Upgradeable",
            "label": "_name",
            "type": "t_string_storage",
            "src": "@openzeppelin/contracts-upgradeable/token/ERC20/ERC20Upgradeable.sol:42"
          },
          {
            "contract": "ERC20Upgradeable",
            "label": "_symbol",
            "type": "t_string_storage",
            "src": "@openzeppelin/contracts-upgradeable/token/ERC20/ERC20Upgradeable.sol:43"
          },
          {
            "contract": "ERC20Upgradeable",
            "label": "__gap",
            "type": "t_array(t_uint256)45_storage",
            "src": "@openzeppelin/contracts-upgradeable/token/ERC20/ERC20Upgradeable.sol:361"
          },
          {
            "contract": "ERC1967UpgradeUpgradeable",
            "label": "__gap",
            "type": "t_array(t_uint256)50_storage",
            "src": "@openzeppelin/contracts-upgradeable/proxy/ERC1967/ERC1967UpgradeUpgradeable.sol:214"
          },
          {
            "contract": "UUPSUpgradeable",
            "label": "__gap",
            "type": "t_array(t_uint256)50_storage",
            "src": "@openzeppelin/contracts-upgradeable/proxy/utils/UUPSUpgradeable.sol:64"
          },
          {
            "contract": "OwnableUpgradeable",
            "label": "_owner",
            "type": "t_address",
            "src": "@openzeppelin/contracts-upgradeable/access/OwnableUpgradeable.sol:21"
          },
          {
            "contract": "OwnableUpgradeable",
            "label": "__gap",
            "type": "t_array(t_uint256)49_storage",
            "src": "@openzeppelin/contracts-upgradeable/access/OwnableUpgradeable.sol:77"
          }
        ],
        "types": {
          "t_address": {
            "label": "address"
          },
          "t_array(t_uint256)49_storage": {
            "label": "uint256[49]"
          },
          "t_uint256": {
            "label": "uint256"
          },
          "t_array(t_uint256)50_storage": {
            "label": "uint256[50]"
          },
          "t_mapping(t_address,t_uint256)": {
            "label": "mapping(address => uint256)"
          },
          "t_mapping(t_address,t_mapping(t_address,t_uint256))": {
            "label": "mapping(address => mapping(address => uint256))"
          },
          "t_string_storage": {
            "label": "string"
          },
          "t_array(t_uint256)45_storage": {
            "label": "uint256[45]"
          },
          "t_bool": {
            "label": "bool"
          }
        }
      }
    }
  }
}
